openscreen/__init__.py
openscreen/config.py
openscreen/request_classes.py
openscreen/resources.py
openscreen/sdk.py
openscreen/session.py
samples/__init__.py
samples/create_batch_dynamic_qr_codes.py
samples/create_dynamic_qr_code.py
samples/send_sms_upon_scan.py
tests/__init__.py
tests/conftest.py
tests/test_assets.py
tests/test_projects.py
openscreen-1.3.1.dist-info/LICENSE
openscreen-1.3.1.dist-info/METADATA
openscreen-1.3.1.dist-info/WHEEL
openscreen-1.3.1.dist-info/top_level.txt
openscreen-1.3.1.dist-info/RECORD
