Metadata-Version: 2.1
Name: openscreen
Version: 1.3.1
Summary: Openscreen's SDK for QR Engage and Tracking
Home-page: https://github.com/Openscreen-Inc/Openscreen-python-sdk
Author: Openscreen-Inc
Author-email: dev@openscreen.com
Project-URL: Bug Tracker, https://github.com/Openscreen-Inc/Openscreen-python-sdk/issues
Project-URL: Changelog, https://api-docs.openscreen.com/changelog
Project-URL: Documentation, https://docs.openscreen.com/overview
Project-URL: API Documentation, https://api-docs.openscreen.com/
Classifier: Programming Language :: Python :: 3.10
Classifier: License :: OSI Approved :: Apache Software License
Classifier: Operating System :: OS Independent
Requires-Python: >=3.10
License-File: LICENSE
Requires-Dist: requests (>=2.27.1)
